decorate_all/__init__.py
decorate_all-0.1.1.dist-info/METADATA
decorate_all-0.1.1.dist-info/WHEEL
decorate_all-0.1.1.dist-info/top_level.txt
decorate_all-0.1.1.dist-info/RECORD
