Metadata-Version: 2.1
Name: decorate-all
Version: 0.1.1
Summary: Apply a decorator to all functions in a module.
Home-page: https://github.com/emendir/py-decorate-all
